{"trial_id": "0001", "hyperparameters": {"space": [{"class_name": "Choice", "config": {"name": "loss_idx", "default": 0, "conditions": [], "values": [0, 1], "ordered": true}}, {"class_name": "Choice", "config": {"name": "optimizer_idx", "default": 0, "conditions": [], "values": [0, 1], "ordered": true}}], "values": {"loss_idx": 0, "optimizer_idx": 1}}, "metrics": {"metrics": {"accuracy": {"direction": "max", "observations": [{"value": [0.8697777986526489], "step": 36}]}, "f1-score": {"direction": "min", "observations": [{"value": [0.6560969948768616], "step": 36}]}, "iou_score": {"direction": "min", "observations": [{"value": [0.48916637897491455], "step": 36}]}, "loss": {"direction": "min", "observations": [{"value": [0.2854312062263489], "step": 36}]}, "val_accuracy": {"direction": "max", "observations": [{"value": [0.8925451636314392], "step": 36}]}, "val_f1-score": {"direction": "min", "observations": [{"value": [0.7104774713516235], "step": 36}]}, "val_iou_score": {"direction": "min", "observations": [{"value": [0.5516720414161682], "step": 36}]}, "val_loss": {"direction": "min", "observations": [{"value": [0.2616034746170044], "step": 36}]}, "learning_rate": {"direction": "min", "observations": [{"value": [0.009999999776482582], "step": 36}]}}}, "score": 0.2616034746170044, "best_step": 36, "status": "COMPLETED", "message": null}